{"trial_id": "3bdf02e3996071ddac1238bee9389fca", "hyperparameters": {"space": [{"class_name": "Boolean", "config": {"name": "structured_data_block_1/normalize", "default": false, "conditions": []}}, {"class_name": "Boolean", "config": {"name": "structured_data_block_1/dense_block_1/use_batchnorm", "default": false, "conditions": []}}, {"class_name": "Choice", "config": {"name": "structured_data_block_1/dense_block_1/num_layers", "default": 2, "conditions": [], "values": [1, 2, 3], "ordered": true}}, {"class_name": "Choice", "config": {"name": "structured_data_block_1/dense_block_1/units_0", "default": 32, "conditions": [], "values": [16, 32, 64, 128, 256, 512, 1024], "ordered": true}}, {"class_name": "Choice", "config": {"name": "structured_data_block_1/dense_block_1/dropout", "default": 0.0, "conditions": [], "values": [0.0, 0.25, 0.5], "ordered": true}}, {"class_name": "Choice", "config": {"name": "structured_data_block_1/dense_block_1/units_1", "default": 32, "conditions": [], "values": [16, 32, 64, 128, 256, 512, 1024], "ordered": true}}, {"class_name": "Choice", "config": {"name": "classification_head_1/dropout", "default": 0, "conditions": [], "values": [0.0, 0.25, 0.5], "ordered": true}}, {"class_name": "Choice", "config": {"name": "optimizer", "default": "adam", "conditions": [], "values": ["adam", "sgd", "adam_weight_decay"], "ordered": false}}, {"class_name": "Choice", "config": {"name": "learning_rate", "default": 0.001, "conditions": [], "values": [0.1, 0.01, 0.001, 0.0001, 2e-05, 1e-05], "ordered": true}}], "values": {"structured_data_block_1/normalize": true, "structured_data_block_1/dense_block_1/use_batchnorm": false, "structured_data_block_1/dense_block_1/num_layers": 2, "structured_data_block_1/dense_block_1/units_0": 32, "structured_data_block_1/dense_block_1/dropout": 0, "structured_data_block_1/dense_block_1/units_1": 32, "classification_head_1/dropout": 0.0, "optimizer": "adam", "learning_rate": 0.1}}, "metrics": {"metrics": {"loss": {"direction": "min", "observations": [{"value": [0.8941971063613892], "step": 0}, {"value": [0.7707765102386475], "step": 1}, {"value": [0.6816433072090149], "step": 2}, {"value": [0.706224799156189], "step": 3}, {"value": [0.6831827759742737], "step": 4}, {"value": [0.6666586995124817], "step": 5}, {"value": [0.6513012051582336], "step": 6}, {"value": [0.6968888640403748], "step": 7}, {"value": [0.6677935123443604], "step": 8}, {"value": [0.6916335225105286], "step": 9}]}, "accuracy": {"direction": "max", "observations": [{"value": [0.6321267485618591], "step": 0}, {"value": [0.6799117922782898], "step": 1}, {"value": [0.7282352447509766], "step": 2}, {"value": [0.7291837334632874], "step": 3}, {"value": [0.7463340759277344], "step": 4}, {"value": [0.7415658235549927], "step": 5}, {"value": [0.7568960189819336], "step": 6}, {"value": [0.7337725758552551], "step": 7}, {"value": [0.7519996166229248], "step": 8}, {"value": [0.7441806793212891], "step": 9}]}, "val_loss": {"direction": "min", "observations": [{"value": [0.9749903082847595], "step": 0}, {"value": [0.7483041286468506], "step": 1}, {"value": [0.7095493078231812], "step": 2}, {"value": [0.716882586479187], "step": 3}, {"value": [0.6786563396453857], "step": 4}, {"value": [0.6512420773506165], "step": 5}, {"value": [0.7333590388298035], "step": 6}, {"value": [0.7301514148712158], "step": 7}, {"value": [0.6965276002883911], "step": 8}, {"value": [0.6795489192008972], "step": 9}]}, "val_accuracy": {"direction": "max", "observations": [{"value": [0.5666941404342651], "step": 0}, {"value": [0.6311239004135132], "step": 1}, {"value": [0.7299299836158752], "step": 2}, {"value": [0.7166529297828674], "step": 3}, {"value": [0.7581309080123901], "step": 4}, {"value": [0.7309592366218567], "step": 5}, {"value": [0.6773363351821899], "step": 6}, {"value": [0.7505146265029907], "step": 7}, {"value": [0.7162412405014038], "step": 8}, {"value": [0.6947303414344788], "step": 9}]}}}, "score": 0.7581309080123901, "best_step": 4, "status": "COMPLETED"}